mcp_context_sdk/__init__.py
mcp_context_sdk/cli.py
mcp_context_sdk/core/builder.py
mcp_context_sdk/core/converter.py
mcp_context_sdk/core/schema_loader.py
mcp_context_sdk/integrations/autogen.py
mcp_context_sdk/integrations/crew.py
mcp_context_sdk/integrations/fastapi.py
mcp_context_sdk/integrations/langchain.py
mcp_context_sdk/integrations/langgraph.py
mcp_context_sdk/integrations/opendevin.py
mcp_context_sdk/utils/validation.py
mcp_context_sdk-0.1.0.dist-info/LICENSE
mcp_context_sdk-0.1.0.dist-info/METADATA
mcp_context_sdk-0.1.0.dist-info/WHEEL
mcp_context_sdk-0.1.0.dist-info/entry_points.txt
mcp_context_sdk-0.1.0.dist-info/RECORD
