Metadata-Version: 2.3
Name: mcp-context-sdk
Version: 0.1.0
Summary: Model Context Protocol SDK for building context-aware AI systems
License: MIT
Keywords: ai,context,sdk,machine-learning,nlp
Author: Ankit Gautam
Author-email: ankit.gautam@example.com
Requires-Python: >=3.8.1,<4.0
Classifier: Development Status :: 4 - Beta
Classifier: Intended Audience :: Developers
Classifier: License :: OSI Approved :: MIT License
Classifier: Programming Language :: Python :: 3
Classifier: Programming Language :: Python :: 3.9
Classifier: Programming Language :: Python :: 3.10
Classifier: Programming Language :: Python :: 3.11
Classifier: Programming Language :: Python :: 3.12
Classifier: Programming Language :: Python :: 3.13
Classifier: Programming Language :: Python :: 3.8
Classifier: Topic :: Scientific/Engineering :: Artificial Intelligence
Classifier: Topic :: Software Development :: Libraries :: Python Modules
Provides-Extra: all
Provides-Extra: fastapi
Requires-Dist: fastapi (>=0.100.0,<0.101.0) ; extra == "fastapi" or extra == "all"
Requires-Dist: pydantic (>=2.0.0,<3.0.0)
Project-URL: Documentation, https://ankit-gautam23.github.io/mcp-context-sdk
Project-URL: Repository, https://github.com/ankit-gautam23/mcp-context-sdk
